{"alignment":"botmid","wrapMode":"loop","spritesheetPath":"axl_rb.png","alignOffX":0,"alignOffY":0,"hitboxes":[],"frames":[{"duration":0.03,"hitboxes":[],"POIs":[],"rect":{"topLeftPoint":{"x":804,"y":4},"botRightPoint":{"x":855,"y":45}},"offset":{"x":0,"y":5}},{"duration":0.03,"hitboxes":[],"POIs":[],"rect":{"topLeftPoint":{"x":648,"y":55},"botRightPoint":{"x":702,"y":106}},"offset":{"x":0,"y":10}},{"duration":0.03,"hitboxes":[],"POIs":[],"rect":{"topLeftPoint":{"x":962,"y":55},"botRightPoint":{"x":1018,"y":110}},"offset":{"x":0,"y":12}},{"duration":0.03,"hitboxes":[],"POIs":[],"rect":{"topLeftPoint":{"x":1,"y":118},"botRightPoint":{"x":57,"y":173}},"offset":{"x":0,"y":12}},{"duration":0.03,"hitboxes":[],"POIs":[],"rect":{"topLeftPoint":{"x":420,"y":55},"botRightPoint":{"x":464,"y":101}},"offset":{"x":1,"y":5}}]}