{"loopStartFrame":0,"alignment":"botmid","wrapMode":"once","spritesheetPath":"mavericksX34.png","customMapName":"","hitboxes":[],"frames":[{"duration":0.066,"xDir":1,"yDir":1,"tags":"","hitboxes":[],"POIs":[{"tags":"wings","x":0,"y":-48}],"rect":{"topLeftPoint":{"x":911,"y":342},"botRightPoint":{"x":954,"y":402}},"offset":{"x":2,"y":-2}},{"duration":0.082,"xDir":1,"yDir":1,"tags":"","hitboxes":[],"POIs":[{"tags":"wings","x":-5,"y":-47}],"rect":{"topLeftPoint":{"x":1,"y":275},"botRightPoint":{"x":39,"y":332}},"offset":{"x":0,"y":-6}},{"duration":0.066,"xDir":1,"yDir":1,"tags":"","hitboxes":[],"POIs":[{"tags":"wings","x":-9,"y":-47}],"rect":{"topLeftPoint":{"x":309,"y":211},"botRightPoint":{"x":348,"y":265}},"offset":{"x":-3,"y":-9}},{"duration":0.066,"xDir":1,"yDir":1,"tags":"","hitboxes":[],"POIs":[{"tags":"wings","x":-9,"y":-48}],"rect":{"topLeftPoint":{"x":350,"y":211},"botRightPoint":{"x":389,"y":265}},"offset":{"x":-3,"y":-10}},{"duration":0.332,"xDir":1,"yDir":1,"tags":"","hitboxes":[],"POIs":[{"tags":"s","x":7,"y":-15},{"tags":"wings","x":-9,"y":-47}],"rect":{"topLeftPoint":{"x":391,"y":211},"botRightPoint":{"x":430,"y":265}},"offset":{"x":-3,"y":-9}},{"duration":0.082,"xDir":1,"yDir":1,"tags":"","hitboxes":[],"POIs":[{"tags":"wings","x":-6,"y":-46}],"rect":{"topLeftPoint":{"x":41,"y":275},"botRightPoint":{"x":79,"y":332}},"offset":{"x":0,"y":-6}},{"duration":0.066,"xDir":1,"yDir":1,"tags":"","hitboxes":[],"POIs":[{"tags":"wings","x":-1,"y":-48}],"rect":{"topLeftPoint":{"x":956,"y":342},"botRightPoint":{"x":999,"y":402}},"offset":{"x":2,"y":-2}}]}