{"loopStartFrame":0,"alignment":"botmid","wrapMode":"once","spritesheetPath":"mavericksX23.png","customMapName":"","hitboxes":[],"frames":[{"duration":0.049,"xDir":1,"yDir":1,"tags":"","hitboxes":[],"POIs":[{"tags":"antler_side","x":22,"y":-37},{"tags":"fireball","x":-8,"y":-30}],"rect":{"topLeftPoint":{"x":678,"y":110},"botRightPoint":{"x":734,"y":149}},"offset":{"x":3,"y":0}},{"duration":0.049,"xDir":1,"yDir":1,"tags":"","hitboxes":[],"POIs":[{"tags":"antler_side","x":24,"y":-41},{"tags":"fireball","x":-1,"y":-37}],"rect":{"topLeftPoint":{"x":618,"y":311},"botRightPoint":{"x":670,"y":356}},"offset":{"x":7,"y":0}},{"duration":0.049,"xDir":1,"yDir":1,"tags":"","hitboxes":[],"POIs":[{"tags":"antler_side","x":25,"y":-42},{"tags":"fireball","x":7,"y":-29}],"rect":{"topLeftPoint":{"x":54,"y":311},"botRightPoint":{"x":105,"y":355}},"offset":{"x":8,"y":0}},{"duration":0.049,"xDir":1,"yDir":1,"tags":"","hitboxes":[],"POIs":[{"tags":"antler_side","x":25,"y":-43},{"tags":"fireball","x":17,"y":-24}],"rect":{"topLeftPoint":{"x":672,"y":311},"botRightPoint":{"x":723,"y":356}},"offset":{"x":8,"y":0}},{"duration":0.032,"xDir":1,"yDir":1,"tags":"","hitboxes":[],"POIs":[{"tags":"antler","x":13,"y":-48},{"tags":"fireball_proj","x":27,"y":-26}],"rect":{"topLeftPoint":{"x":343,"y":421},"botRightPoint":{"x":390,"y":472}},"offset":{"x":7,"y":0}},{"duration":0.032,"xDir":1,"yDir":1,"tags":"","hitboxes":[],"POIs":[{"tags":"antler","x":12,"y":-48}],"rect":{"topLeftPoint":{"x":392,"y":421},"botRightPoint":{"x":445,"y":472}},"offset":{"x":10,"y":0}},{"duration":0.032,"xDir":1,"yDir":1,"tags":"","hitboxes":[],"POIs":[{"tags":"antler","x":12,"y":-50}],"rect":{"topLeftPoint":{"x":789,"y":545},"botRightPoint":{"x":834,"y":602}},"offset":{"x":7,"y":0}},{"duration":0.032,"xDir":1,"yDir":1,"tags":"","hitboxes":[],"POIs":[{"tags":"antler","x":12,"y":-52}],"rect":{"topLeftPoint":{"x":379,"y":752},"botRightPoint":{"x":416,"y":819}},"offset":{"x":4,"y":0}},{"duration":0.299,"xDir":1,"yDir":1,"tags":"","hitboxes":[],"POIs":[{"tags":"antler","x":12,"y":-50}],"rect":{"topLeftPoint":{"x":836,"y":545},"botRightPoint":{"x":881,"y":602}},"offset":{"x":7,"y":0}}]}