{"alignment":"center","wrapMode":"loop","spritesheetPath":"effects2.png","alignOffX":0,"alignOffY":0,"hitboxes":[{"width":17,"height":18,"flag":1,"isTrigger":true,"offset":{"x":0,"y":0}}],"frames":[{"duration":0.06,"hitboxes":[],"POIs":[],"rect":{"topLeftPoint":{"x":587,"y":48},"botRightPoint":{"x":604,"y":66}},"offset":{"x":0,"y":0}},{"duration":0.06,"hitboxes":[],"POIs":[],"rect":{"topLeftPoint":{"x":502,"y":74},"botRightPoint":{"x":523,"y":96}},"offset":{"x":0,"y":0}},{"duration":0.06,"hitboxes":[],"POIs":[],"rect":{"topLeftPoint":{"x":151,"y":106},"botRightPoint":{"x":174,"y":130}},"offset":{"x":0,"y":0}},{"duration":0.06,"hitboxes":[],"POIs":[],"rect":{"topLeftPoint":{"x":525,"y":74},"botRightPoint":{"x":546,"y":96}},"offset":{"x":0,"y":0}}]}