{"alignment":"center","wrapMode":"once","spritesheetPath":"crackedWalls.png","alignOffX":0,"alignOffY":0,"hitboxes":[],"frames":[{"duration":0.03,"hitboxes":[],"POIs":[],"rect":{"topLeftPoint":{"x":63,"y":4},"botRightPoint":{"x":71,"y":12}},"offset":{"x":0,"y":0}},{"duration":0.03,"hitboxes":[],"POIs":[],"rect":{"topLeftPoint":{"x":73,"y":4},"botRightPoint":{"x":84,"y":12}},"offset":{"x":0,"y":0}},{"duration":0.03,"hitboxes":[],"POIs":[],"rect":{"topLeftPoint":{"x":17,"y":4},"botRightPoint":{"x":21,"y":10}},"offset":{"x":0,"y":0}}]}