{"loopStartFrame":0,"alignment":"botmid","wrapMode":"once","spritesheetPath":"mavericksX33.png","customMapName":"","hitboxes":[],"frames":[{"duration":0.049,"xDir":1,"yDir":1,"tags":"","hitboxes":[],"POIs":[],"rect":{"topLeftPoint":{"x":604,"y":145},"botRightPoint":{"x":677,"y":200}},"offset":{"x":0,"y":0}},{"duration":0.049,"xDir":1,"yDir":1,"tags":"","hitboxes":[{"width":31,"height":65,"flag":0,"isTrigger":true,"offset":{"x":41,"y":-13}}],"POIs":[],"rect":{"topLeftPoint":{"x":931,"y":572},"botRightPoint":{"x":1022,"y":656}},"offset":{"x":10,"y":0}},{"duration":0.132,"xDir":1,"yDir":1,"tags":"","hitboxes":[{"width":55,"height":20,"flag":0,"isTrigger":true,"offset":{"x":11,"y":-14}}],"POIs":[],"rect":{"topLeftPoint":{"x":600,"y":417},"botRightPoint":{"x":672,"y":482}},"offset":{"x":14,"y":0}},{"duration":0.132,"xDir":1,"yDir":1,"tags":"","hitboxes":[],"POIs":[],"rect":{"topLeftPoint":{"x":606,"y":277},"botRightPoint":{"x":675,"y":337}},"offset":{"x":0,"y":0}}]}