{"loopStartFrame":0,"alignment":"botmid","wrapMode":"loop","spritesheetPath":"mavericksX34.png","customMapName":"","hitboxes":[],"frames":[{"duration":0.032,"xDir":1,"yDir":1,"tags":"","hitboxes":[],"POIs":[],"rect":{"topLeftPoint":{"x":435,"y":482},"botRightPoint":{"x":513,"y":548}},"offset":{"x":6,"y":0}},{"duration":0.032,"xDir":1,"yDir":1,"tags":"","hitboxes":[],"POIs":[],"rect":{"topLeftPoint":{"x":380,"y":410},"botRightPoint":{"x":458,"y":471}},"offset":{"x":6,"y":-3}},{"duration":0.032,"xDir":1,"yDir":1,"tags":"","hitboxes":[],"POIs":[],"rect":{"topLeftPoint":{"x":347,"y":482},"botRightPoint":{"x":433,"y":547}},"offset":{"x":2,"y":0}}]}