{"alignment":"center","wrapMode":"once","spritesheetPath":"effects2.png","alignOffX":0,"alignOffY":0,"hitboxes":[],"frames":[{"duration":0.03,"hitboxes":[],"POIs":[],"rect":{"topLeftPoint":{"x":447,"y":4},"botRightPoint":{"x":456,"y":13}},"offset":{"x":0,"y":0}},{"duration":0.03,"hitboxes":[],"POIs":[],"rect":{"topLeftPoint":{"x":81,"y":4},"botRightPoint":{"x":86,"y":9}},"offset":{"x":0,"y":0}},{"duration":0.03,"hitboxes":[],"POIs":[],"rect":{"topLeftPoint":{"x":37,"y":4},"botRightPoint":{"x":39,"y":6}},"offset":{"x":0,"y":0}}]}