{"loopStartFrame":0,"alignment":"center","wrapMode":"once","spritesheetPath":"effects3.png","hitboxes":[],"frames":[{"duration":0.033,"xDir":1,"yDir":1,"tags":"","hitboxes":[],"POIs":[],"rect":{"topLeftPoint":{"x":509,"y":4},"botRightPoint":{"x":555,"y":15}},"offset":{"x":0,"y":0}},{"duration":0.033,"xDir":1,"yDir":1,"tags":"","hitboxes":[],"POIs":[],"rect":{"topLeftPoint":{"x":391,"y":4},"botRightPoint":{"x":435,"y":13}},"offset":{"x":0,"y":0}},{"duration":0.033,"xDir":1,"yDir":1,"tags":"","hitboxes":[],"POIs":[],"rect":{"topLeftPoint":{"x":180,"y":4},"botRightPoint":{"x":222,"y":11}},"offset":{"x":0,"y":0}},{"duration":0.033,"xDir":1,"yDir":1,"tags":"","hitboxes":[],"POIs":[],"rect":{"topLeftPoint":{"x":97,"y":4},"botRightPoint":{"x":138,"y":9}},"offset":{"x":0,"y":0}}]}