{"loopStartFrame":0,"alignment":"botmid","wrapMode":"once","spritesheetPath":"doppler.png","hitboxes":[],"frames":[{"duration":0.099,"xDir":1,"yDir":1,"tags":"","hitboxes":[],"POIs":[],"rect":{"topLeftPoint":{"x":47,"y":89},"botRightPoint":{"x":87,"y":144}},"offset":{"x":-1,"y":0}},{"duration":0.099,"xDir":1,"yDir":1,"tags":"","hitboxes":[],"POIs":[],"rect":{"topLeftPoint":{"x":88,"y":91},"botRightPoint":{"x":132,"y":144}},"offset":{"x":-1,"y":0}},{"duration":0.099,"xDir":1,"yDir":1,"tags":"","hitboxes":[],"POIs":[],"rect":{"topLeftPoint":{"x":47,"y":89},"botRightPoint":{"x":87,"y":144}},"offset":{"x":-1,"y":0}},{"duration":0.099,"xDir":1,"yDir":1,"tags":"","hitboxes":[],"POIs":[],"rect":{"topLeftPoint":{"x":88,"y":91},"botRightPoint":{"x":132,"y":144}},"offset":{"x":-1,"y":0}},{"duration":0.099,"xDir":1,"yDir":1,"tags":"","hitboxes":[],"POIs":[],"rect":{"topLeftPoint":{"x":47,"y":89},"botRightPoint":{"x":87,"y":144}},"offset":{"x":-1,"y":0}},{"duration":0.099,"xDir":1,"yDir":1,"tags":"","hitboxes":[],"POIs":[],"rect":{"topLeftPoint":{"x":88,"y":91},"botRightPoint":{"x":132,"y":144}},"offset":{"x":-1,"y":0}},{"duration":0.099,"xDir":1,"yDir":1,"tags":"","hitboxes":[],"POIs":[],"rect":{"topLeftPoint":{"x":47,"y":89},"botRightPoint":{"x":87,"y":144}},"offset":{"x":-1,"y":0}},{"duration":0.332,"xDir":1,"yDir":1,"tags":"","hitboxes":[],"POIs":[],"rect":{"topLeftPoint":{"x":88,"y":91},"botRightPoint":{"x":132,"y":144}},"offset":{"x":-1,"y":0}}]}