{"loopStartFrame":0,"alignment":"center","wrapMode":"once","spritesheetPath":"vileNewWeapons.png","customMapName":"","hitboxes":[],"frames":[{"duration":0.032,"xDir":1,"yDir":1,"tags":"","hitboxes":[],"POIs":[],"rect":{"topLeftPoint":{"x":3,"y":272},"botRightPoint":{"x":17,"y":286}},"offset":{"x":0,"y":0}},{"duration":0.032,"xDir":1,"yDir":1,"tags":"","hitboxes":[],"POIs":[],"rect":{"topLeftPoint":{"x":20,"y":271},"botRightPoint":{"x":36,"y":287}},"offset":{"x":0,"y":0}},{"duration":0.032,"xDir":1,"yDir":1,"tags":"","hitboxes":[],"POIs":[],"rect":{"topLeftPoint":{"x":38,"y":271},"botRightPoint":{"x":54,"y":287}},"offset":{"x":0,"y":0}}]}