{"loopStartFrame":0,"alignment":"botmid","wrapMode":"once","spritesheetPath":"XDefault.png","hitboxes":[],"frames":[{"duration":0.03,"xDir":1,"yDir":1,"tags":"","hitboxes":[],"POIs":[{"tags":"h","x":0,"y":-28}],"rect":{"topLeftPoint":{"x":10,"y":1099},"botRightPoint":{"x":41,"y":1135}},"offset":{"x":0,"y":0}},{"duration":0.03,"xDir":1,"yDir":1,"tags":"","hitboxes":[],"POIs":[{"tags":"h","x":1,"y":-27}],"rect":{"topLeftPoint":{"x":50,"y":1099},"botRightPoint":{"x":86,"y":1135}},"offset":{"x":-5,"y":0}},{"duration":0.03,"xDir":1,"yDir":1,"tags":"","hitboxes":[{"tags":"","width":38,"height":20,"flag":0,"isTrigger":true,"offset":{"x":-8,"y":-22}}],"POIs":[{"tags":"h","x":3,"y":-24}],"rect":{"topLeftPoint":{"x":102,"y":1095},"botRightPoint":{"x":140,"y":1135}},"offset":{"x":-6,"y":0}},{"duration":0.03,"xDir":1,"yDir":1,"tags":"","hitboxes":[{"tags":"","width":35,"height":40,"flag":0,"isTrigger":true,"offset":{"x":31,"y":-5}}],"POIs":[{"tags":"h","x":11,"y":-24}],"rect":{"topLeftPoint":{"x":156,"y":1089},"botRightPoint":{"x":224,"y":1135}},"offset":{"x":16,"y":0}},{"duration":0.03,"xDir":1,"yDir":1,"tags":"","hitboxes":[{"tags":"","width":55,"height":57,"flag":0,"isTrigger":true,"offset":{"x":29,"y":9}}],"POIs":[{"tags":"h","x":10,"y":-23}],"rect":{"topLeftPoint":{"x":227,"y":1086},"botRightPoint":{"x":304,"y":1143}},"offset":{"x":18,"y":9}},{"duration":0.03,"xDir":1,"yDir":1,"tags":"","hitboxes":[{"tags":"","width":47,"height":30,"flag":0,"isTrigger":true,"offset":{"x":33,"y":8}}],"POIs":[{"tags":"h","x":10,"y":-23}],"rect":{"topLeftPoint":{"x":309,"y":1093},"botRightPoint":{"x":387,"y":1143}},"offset":{"x":19,"y":8}},{"duration":0.03,"xDir":1,"yDir":1,"tags":"","hitboxes":[{"tags":"","width":47,"height":30,"flag":0,"isTrigger":true,"offset":{"x":33,"y":8}}],"POIs":[{"tags":"h","x":10,"y":-23}],"rect":{"topLeftPoint":{"x":3,"y":1156},"botRightPoint":{"x":80,"y":1196}},"offset":{"x":18,"y":8}},{"duration":0.03,"xDir":1,"yDir":1,"tags":"","hitboxes":[],"POIs":[{"tags":"h","x":10,"y":-23}],"rect":{"topLeftPoint":{"x":87,"y":1156},"botRightPoint":{"x":139,"y":1196}},"offset":{"x":6,"y":8}},{"duration":0.03,"xDir":1,"yDir":1,"tags":"","hitboxes":[],"POIs":[{"tags":"h","x":10,"y":-23}],"rect":{"topLeftPoint":{"x":149,"y":1156},"botRightPoint":{"x":188,"y":1193}},"offset":{"x":-1,"y":5}},{"duration":0.03,"xDir":1,"yDir":1,"tags":"","hitboxes":[],"POIs":[{"tags":"h","x":10,"y":-23}],"rect":{"topLeftPoint":{"x":198,"y":1156},"botRightPoint":{"x":235,"y":1189}},"offset":{"x":-2,"y":1}},{"duration":0.03,"xDir":1,"yDir":1,"tags":"","hitboxes":[],"POIs":[{"tags":"h","x":10,"y":-23}],"rect":{"topLeftPoint":{"x":248,"y":1156},"botRightPoint":{"x":285,"y":1189}},"offset":{"x":-2,"y":1}},{"duration":0.03,"xDir":1,"yDir":1,"tags":"","hitboxes":[],"POIs":[{"tags":"h","x":5,"y":-26}],"rect":{"topLeftPoint":{"x":300,"y":1155},"botRightPoint":{"x":331,"y":1189}},"offset":{"x":-2,"y":0}}]}