{"loopStartFrame":0,"alignment":"botmid","wrapMode":"once","spritesheetPath":"mavericks.png","hitboxes":[],"frames":[{"duration":0.066,"xDir":1,"yDir":1,"tags":"","hitboxes":[],"POIs":[],"rect":{"topLeftPoint":{"x":1169,"y":866},"botRightPoint":{"x":1223,"y":921}},"offset":{"x":-3,"y":0}},{"duration":0.066,"xDir":1,"yDir":1,"tags":"","hitboxes":[],"POIs":[],"rect":{"topLeftPoint":{"x":1096,"y":862},"botRightPoint":{"x":1165,"y":922}},"offset":{"x":-1,"y":0}},{"duration":0.066,"xDir":1,"yDir":1,"tags":"","hitboxes":[],"POIs":[],"rect":{"topLeftPoint":{"x":1028,"y":835},"botRightPoint":{"x":1089,"y":924}},"offset":{"x":-3,"y":0}}]}