{"loopStartFrame":0,"alignment":"botmid","wrapMode":"once","spritesheetPath":"mavericksX2.png","customMapName":"","hitboxes":[],"frames":[{"duration":0.049,"xDir":1,"yDir":1,"tags":"","hitboxes":[],"POIs":[],"rect":{"topLeftPoint":{"x":371,"y":137},"botRightPoint":{"x":423,"y":193}},"offset":{"x":0,"y":0}},{"duration":0.132,"xDir":1,"yDir":1,"tags":"","hitboxes":[],"POIs":[],"rect":{"topLeftPoint":{"x":431,"y":142},"botRightPoint":{"x":483,"y":193}},"offset":{"x":1,"y":0}},{"duration":0.066,"xDir":1,"yDir":1,"tags":"","hitboxes":[],"POIs":[],"rect":{"topLeftPoint":{"x":371,"y":137},"botRightPoint":{"x":423,"y":193}},"offset":{"x":0,"y":0}}]}